<annotation>
	<folder>nakib mixed</folder>
	<filename>mixed (48).jpg</filename>
	<path>D:\14th semester\Labeling\New folder\nakib mixed\mixed (48).jpg</path>
	<source>
		<database>Unknown</database>
	</source>
	<size>
		<width>4608</width>
		<height>3456</height>
		<depth>3</depth>
	</size>
	<segmented>0</segmented>
	<object>
		<name>cng</name>
		<pose>Unspecified</pose>
		<truncated>0</truncated>
		<difficult>0</difficult>
		<bndbox>
			<xmin>156</xmin>
			<ymin>683</ymin>
			<xmax>961</xmax>
			<ymax>1562</ymax>
		</bndbox>
	</object>
	<object>
		<name>cng</name>
		<pose>Unspecified</pose>
		<truncated>0</truncated>
		<difficult>0</difficult>
		<bndbox>
			<xmin>2224</xmin>
			<ymin>730</ymin>
			<xmax>3330</xmax>
			<ymax>1594</ymax>
		</bndbox>
	</object>
	<object>
		<name>bicycle</name>
		<pose>Unspecified</pose>
		<truncated>0</truncated>
		<difficult>0</difficult>
		<bndbox>
			<xmin>1388</xmin>
			<ymin>1036</ymin>
			<xmax>1635</xmax>
			<ymax>1430</ymax>
		</bndbox>
	</object>
	<object>
		<name>car</name>
		<pose>Unspecified</pose>
		<truncated>0</truncated>
		<difficult>0</difficult>
		<bndbox>
			<xmin>1246</xmin>
			<ymin>762</ymin>
			<xmax>2235</xmax>
			<ymax>1288</ymax>
		</bndbox>
	</object>
	<object>
		<name>rickshaw</name>
		<pose>Unspecified</pose>
		<truncated>0</truncated>
		<difficult>0</difficult>
		<bndbox>
			<xmin>930</xmin>
			<ymin>830</ymin>
			<xmax>1040</xmax>
			<ymax>1067</ymax>
		</bndbox>
	</object>
</annotation>
