<annotation>
	<folder>nakib mixed</folder>
	<filename>mixed (28).jpg</filename>
	<path>D:\14th semester\Labeling\New folder\nakib mixed\mixed (28).jpg</path>
	<source>
		<database>Unknown</database>
	</source>
	<size>
		<width>3120</width>
		<height>4160</height>
		<depth>3</depth>
	</size>
	<segmented>0</segmented>
	<object>
		<name>cng</name>
		<pose>Unspecified</pose>
		<truncated>0</truncated>
		<difficult>0</difficult>
		<bndbox>
			<xmin>613</xmin>
			<ymin>2197</ymin>
			<xmax>1206</xmax>
			<ymax>2730</ymax>
		</bndbox>
	</object>
	<object>
		<name>car</name>
		<pose>Unspecified</pose>
		<truncated>1</truncated>
		<difficult>0</difficult>
		<bndbox>
			<xmin>1</xmin>
			<ymin>2237</ymin>
			<xmax>73</xmax>
			<ymax>2420</ymax>
		</bndbox>
	</object>
	<object>
		<name>bus</name>
		<pose>Unspecified</pose>
		<truncated>1</truncated>
		<difficult>0</difficult>
		<bndbox>
			<xmin>1</xmin>
			<ymin>2070</ymin>
			<xmax>373</xmax>
			<ymax>2363</ymax>
		</bndbox>
	</object>
	<object>
		<name>truck</name>
		<pose>Unspecified</pose>
		<truncated>0</truncated>
		<difficult>0</difficult>
		<bndbox>
			<xmin>833</xmin>
			<ymin>1763</ymin>
			<xmax>2293</xmax>
			<ymax>2657</ymax>
		</bndbox>
	</object>
</annotation>
