<annotation>
	<folder>nakib mixed</folder>
	<filename>mixed (44).jpg</filename>
	<path>D:\14th semester\Labeling\New folder\nakib mixed\mixed (44).jpg</path>
	<source>
		<database>Unknown</database>
	</source>
	<size>
		<width>3456</width>
		<height>4608</height>
		<depth>3</depth>
	</size>
	<segmented>0</segmented>
	<object>
		<name>van</name>
		<pose>Unspecified</pose>
		<truncated>0</truncated>
		<difficult>0</difficult>
		<bndbox>
			<xmin>335</xmin>
			<ymin>2129</ymin>
			<xmax>2257</xmax>
			<ymax>3043</ymax>
		</bndbox>
	</object>
	<object>
		<name>truck</name>
		<pose>Unspecified</pose>
		<truncated>1</truncated>
		<difficult>0</difficult>
		<bndbox>
			<xmin>1</xmin>
			<ymin>1736</ymin>
			<xmax>928</xmax>
			<ymax>2637</ymax>
		</bndbox>
	</object>
	<object>
		<name>truck</name>
		<pose>Unspecified</pose>
		<truncated>0</truncated>
		<difficult>0</difficult>
		<bndbox>
			<xmin>771</xmin>
			<ymin>1729</ymin>
			<xmax>1271</xmax>
			<ymax>2229</ymax>
		</bndbox>
	</object>
</annotation>
